vbio/__init__.py
vbio/bot.py
vbio/logging.py
vbio/types.py
vbio/servers/__init__.py
vbio/servers/cherrypy.py
vbio/servers/flask.py
vbio/servers/longpool.py
vbio-0.0.6.dist-info/LICENSE.txt
vbio-0.0.6.dist-info/METADATA
vbio-0.0.6.dist-info/WHEEL
vbio-0.0.6.dist-info/top_level.txt
vbio-0.0.6.dist-info/RECORD
