Metadata-Version: 2.1
Name: vbio
Version: 0.0.6
Summary: Python модуль для написания скриптов, использующих Callback API для социальной сети Вконтакте (vk.com)
Home-page: https://github.com/yilbegan/vbio
Author: yilbegan
License: MIT
Platform: UNKNOWN
Classifier: License :: OSI Approved :: Apache Software License
Classifier: Operating System :: OS Independent
Classifier: Programming Language :: Python
Classifier: Programming Language :: Python :: 2
Classifier: Programming Language :: Python :: 2.7
Classifier: Programming Language :: Python :: 3
Classifier: Programming Language :: Python :: 3.4
Classifier: Programming Language :: Python :: 3.5
Classifier: Programming Language :: Python :: 3.6
Classifier: Programming Language :: Python :: 3.7
Classifier: Programming Language :: Python :: Implementation :: PyPy
Classifier: Programming Language :: Python :: Implementation :: CPython
Requires-Dist: requests
Provides-Extra: color
Requires-Dist: colorama ; extra == 'color'
Provides-Extra: webhook
Requires-Dist: Flask ; extra == 'webhook'
